healthcheck_decorator/conf.py
healthcheck_decorator/heathcheck.py
healthcheck_decorator/monitor.py
healthcheck_decorator-0.1.0.dist-info/METADATA
healthcheck_decorator-0.1.0.dist-info/WHEEL
healthcheck_decorator-0.1.0.dist-info/top_level.txt
healthcheck_decorator-0.1.0.dist-info/RECORD
